azmessaging/__init__.py
azmessaging/apps.py
azmessaging/default_settings.py
azmessaging/utils.py
azmessaging/channels/__init__.py
azmessaging/channels/base.py
azmessaging/channels/pushnotifications.py
azmessaging/channels/sms.py
azmessaging/channels/telegram.py
azmessaging/exceptions/__init__.py
azmessaging/exceptions/exceptions.py
azmessaging/locale/en/LC_MESSAGES/django.mo
azmessaging/locale/en/LC_MESSAGES/django.po
azmessaging/models/__init__.py
azmessaging/models/enum_django.py
azmessaging/models/enums.py
azmessaging/pushnotifications/__init__.py
azmessaging/pushnotifications/fcmdjango.py
azmessaging/pushnotifications/pushabstract.py
azmessaging/readers/__init__.py
azmessaging/readers/bases.py
azmessaging/readers/defaults.py
azmessaging/readers/pushnotifications/__init__.py
azmessaging/readers/pushnotifications/config.py
azmessaging/readers/pushnotifications/readermixin.py
azmessaging/readers/sms/__init__.py
azmessaging/readers/sms/config.py
azmessaging/readers/sms/readermixin.py
azmessaging/readers/telegram/__init__.py
azmessaging/readers/telegram/config.py
azmessaging/readers/telegram/readermixin.py
azmessaging/sms/__init__.py
azmessaging/sms/smsabstract.py
azmessaging/sms/sns.py
azmessaging/sms/twilio.py
azmessaging/telegram/__init__.py
azmessaging/telegram/default.py
azmessaging/telegram/telegramabstract.py
az_messaging-1.3.0.dist-info/LICENSE
az_messaging-1.3.0.dist-info/METADATA
az_messaging-1.3.0.dist-info/WHEEL
az_messaging-1.3.0.dist-info/top_level.txt
az_messaging-1.3.0.dist-info/RECORD
